image2ascii/__init__.py
image2ascii/cli.py
image2ascii/color.py
image2ascii/config.py
image2ascii/core.py
image2ascii/db.py
image2ascii/geometry.py
image2ascii/output.py
image2ascii/test.py
image2ascii/utils.py
image2ascii/wsgi.py
image2ascii/flags/Abkhazia.png
image2ascii/flags/Afghanistan.png
image2ascii/flags/Albania.png
image2ascii/flags/Algeria.png
image2ascii/flags/Andorra.png
image2ascii/flags/Angola.png
image2ascii/flags/Antigua and Barbuda.png
image2ascii/flags/Argentina.png
image2ascii/flags/Armenia.png
image2ascii/flags/Artsakh.png
image2ascii/flags/Australia.png
image2ascii/flags/Austria.png
image2ascii/flags/Azerbaijan.png
image2ascii/flags/Bahamas.png
image2ascii/flags/Bahrain.png
image2ascii/flags/Bangladesh.png
image2ascii/flags/Barbados.png
image2ascii/flags/Belarus.png
image2ascii/flags/Belgium.png
image2ascii/flags/Belize.png
image2ascii/flags/Benin.png
image2ascii/flags/Bhutan.png
image2ascii/flags/Bolivia.png
image2ascii/flags/Bosnia and Herzegovina.png
image2ascii/flags/Botswana.png
image2ascii/flags/Brazil.png
image2ascii/flags/Brunei.png
image2ascii/flags/Bulgaria.png
image2ascii/flags/Burkina Faso.png
image2ascii/flags/Burundi.png
image2ascii/flags/Cambodia.png
image2ascii/flags/Cameroon.png
image2ascii/flags/Canada.png
image2ascii/flags/Cape Verde.png
image2ascii/flags/Central African Republic.png
image2ascii/flags/Chad.png
image2ascii/flags/Chile.png
image2ascii/flags/China.png
image2ascii/flags/Colombia.png
image2ascii/flags/Comoros.png
image2ascii/flags/Cook Islands.png
image2ascii/flags/Costa Rica.png
image2ascii/flags/Croatia.png
image2ascii/flags/Cuba.png
image2ascii/flags/Cyprus.png
image2ascii/flags/Czech Republic.png
image2ascii/flags/Democratic Republic of the Congo.png
image2ascii/flags/Denmark.png
image2ascii/flags/Djibouti.png
image2ascii/flags/Dominica.png
image2ascii/flags/Dominican Republic.png
image2ascii/flags/East Timor.png
image2ascii/flags/Ecuador.png
image2ascii/flags/Egypt.png
image2ascii/flags/El Salvador.png
image2ascii-0.6.2.dist-info/LICENSE
image2ascii-0.6.2.dist-info/METADATA
image2ascii-0.6.2.dist-info/WHEEL
image2ascii-0.6.2.dist-info/entry_points.txt
image2ascii-0.6.2.dist-info/top_level.txt
image2ascii-0.6.2.dist-info/RECORD
