Metadata-Version: 2.1
Name: image2ascii
Version: 0.6.2
Summary: Fancy image to ASCII/ANSI converter
Author-email: Robert Huselius <robert@huseli.us>
License: GNU GENERAL PUBLIC LICENSE
Project-URL: Repository, https://github.com/Eboreg/image2ascii
Classifier: Development Status :: 4 - Beta
Classifier: Environment :: Console
Classifier: Environment :: Web Environment
Classifier: License :: OSI Approved :: GNU General Public License v3 (GPLv3)
Classifier: Topic :: Artistic Software
Classifier: Topic :: Multimedia :: Graphics :: Graphics Conversion
Requires-Python: >=3.5
License-File: LICENSE
Requires-Dist: colorama >=0.4.4
Requires-Dist: matplotlib ==3.*
Requires-Dist: numpy ==1.*
Requires-Dist: Pillow ==8.*
Provides-Extra: www
Requires-Dist: Flask ==2.* ; extra == 'www'
Requires-Dist: requests ==2.* ; extra == 'www'
Requires-Dist: uWSGI ==2.* ; extra == 'www'
